odoo/addons/l10n_es_vat_book_oss/README.rst
odoo/addons/l10n_es_vat_book_oss/__init__.py
odoo/addons/l10n_es_vat_book_oss/__manifest__.py
odoo/addons/l10n_es_vat_book_oss/i18n/l10n_es_vat_book_oss.pot
odoo/addons/l10n_es_vat_book_oss/models/__init__.py
odoo/addons/l10n_es_vat_book_oss/models/aeat_vat_book_map_lines.py
odoo/addons/l10n_es_vat_book_oss/models/l10n_es_vat_book.py
odoo/addons/l10n_es_vat_book_oss/readme/CONFIGURE.rst
odoo/addons/l10n_es_vat_book_oss/readme/CONTRIBUTORS.rst
odoo/addons/l10n_es_vat_book_oss/readme/DESCRIPTION.rst
odoo/addons/l10n_es_vat_book_oss/readme/INSTALL.rst
odoo/addons/l10n_es_vat_book_oss/readme/ROADMAP.rst
odoo/addons/l10n_es_vat_book_oss/readme/USAGE.rst
odoo/addons/l10n_es_vat_book_oss/static/description/icon.png
odoo/addons/l10n_es_vat_book_oss/static/description/index.html
odoo13_addon_l10n_es_vat_book_oss-13.0.1.0.1.dev3.dist-info/METADATA
odoo13_addon_l10n_es_vat_book_oss-13.0.1.0.1.dev3.dist-info/WHEEL
odoo13_addon_l10n_es_vat_book_oss-13.0.1.0.1.dev3.dist-info/top_level.txt
odoo13_addon_l10n_es_vat_book_oss-13.0.1.0.1.dev3.dist-info/RECORD
